storage_script/__init__.py
storage_script/__main__.py
storage_script/cli/__init__.py
storage_script/cli/download.py
storage_script/cli/upload.py
storage_script/download.py
storage_script/progress.py
storage_script/upload.py
storage_script-0.2.4.dist-info/entry_points.txt
storage_script-0.2.4.dist-info/WHEEL
storage_script-0.2.4.dist-info/METADATA
storage_script-0.2.4.dist-info/RECORD
