Metadata-Version: 2.1
Name: storage-script
Version: 0.2.4
Summary: Rasa Storage Script
Home-page: https://github.tools.sap/dsx/storage-script
Author: Venkatesh
Author-email: venkatesh.damodar.pai@sap.com
Requires-Python: >=3.7,<4.0
Classifier: Programming Language :: Python :: 3
Classifier: Programming Language :: Python :: 3.7
Classifier: Programming Language :: Python :: 3.8
Classifier: Programming Language :: Python :: 3.9
Requires-Dist: boto3 (==1.16.51)
Project-URL: Repository, https://github.tools.sap/dsx/storage-script
